README.rst
setup.cfg
setup.py
peek_client/PeekClientConfig.py
peek_client/PeekClientConfigTest.py
peek_client/__init__.py
peek_client/run_peek_client.py
peek_client/run_peek_client_build_only.py
peek_client/winsvc_peek_client.py
peek_client.egg-info/PKG-INFO
peek_client.egg-info/SOURCES.txt
peek_client.egg-info/dependency_links.txt
peek_client.egg-info/entry_points.txt
peek_client.egg-info/not-zip-safe
peek_client.egg-info/requires.txt
peek_client.egg-info/top_level.txt
peek_client/backend/ClientObservable.py
peek_client/backend/SiteRootResource.py
peek_client/backend/__init__.py
peek_client/plugin/ClientFrontendBuildersMixin.py
peek_client/plugin/ClientPluginLoader.py
peek_client/plugin/ClientPluginLoaderTest.py
peek_client/plugin/PeekClientPlatformHook.py
peek_client/plugin/__init__.py
peek_client/sw_install/PeekSwInstallManager.py
peek_client/sw_install/PluginSwInstallManager.py
peek_client/sw_install/__init__.py