Metadata-Version: 1.1
Name: peek-client
Version: 1.3.2
Summary: Peek Platform - Client Service
Home-page: https://github.com/Synerty/peek-client
Author: Synerty
Author-email: contact@synerty.com
License: UNKNOWN
Download-URL: https://github.com/Synerty/peek-client/tarball/1.3.2
Keywords: Peek,Python,Platform,synerty
Platform: UNKNOWN
Classifier: Programming Language :: Python :: 3.5
